scicheat/__init__.py
scicheat/dataloader.py
scicheat-0.2.dist-info/LICENSE
scicheat-0.2.dist-info/METADATA
scicheat-0.2.dist-info/WHEEL
scicheat-0.2.dist-info/top_level.txt
scicheat-0.2.dist-info/RECORD
