Metadata-Version: 2.1
Name: scicheat
Version: 0.2
Summary: A package to help gain quick insights into a new dataset
Home-page: https://github.com/andrewjkuo/scicheat
Author: Andrew Kuo
License: MIT
Platform: UNKNOWN
Requires-Dist: matplotlib
Requires-Dist: numpy
Requires-Dist: pandas
Requires-Dist: scikit-learn
Requires-Dist: seaborn
